binance/__init__.py
binance/client.py
binance/depthcache.py
binance/enums.py
binance/exceptions.py
binance/helpers.py
binance/websockets.py
python_binance_yori-1.0.dist-info/LICENSE
python_binance_yori-1.0.dist-info/METADATA
python_binance_yori-1.0.dist-info/WHEEL
python_binance_yori-1.0.dist-info/top_level.txt
python_binance_yori-1.0.dist-info/RECORD
